<?xml version="1.0" encoding="UTF-8"?>
<persistence version="2.1" xmlns="http://xmlns.jcp.org/xml/ns/persistence" xmlns:xsi="http://www.w3.org/2001/XMLSchema-instance" xsi:schemaLocation="http://xmlns.jcp.org/xml/ns/persistence http://xmlns.jcp.org/xml/ns/persistence/persistence_2_1.xsd">
  <persistence-unit name="PU_talleres" transaction-type="JTA">
    <jta-data-source>java:app/app_jndi</jta-data-source>
    <class>sv.edu.fmocc.tpi_2019.historial.cars.historycars.entities.Diagnostico</class>
    <class>sv.edu.fmocc.tpi_2019.historial.cars.historycars.entities.Especialidad</class>
    <class>sv.edu.fmocc.tpi_2019.historial.cars.historycars.entities.EstadoPaso</class>
    <class>sv.edu.fmocc.tpi_2019.historial.cars.historycars.entities.HistorialPropietario</class>
    <class>sv.edu.fmocc.tpi_2019.historial.cars.historycars.entities.Marca</class>
    <class>sv.edu.fmocc.tpi_2019.historial.cars.historycars.entities.Modelo</class>
    <class>sv.edu.fmocc.tpi_2019.historial.cars.historycars.entities.Parte</class>
    <class>sv.edu.fmocc.tpi_2019.historial.cars.historycars.entities.Paso</class>
    <class>sv.edu.fmocc.tpi_2019.historial.cars.historycars.entities.PasoProceso</class>
    <class>sv.edu.fmocc.tpi_2019.historial.cars.historycars.entities.PasoReparacion</class>
    <class>sv.edu.fmocc.tpi_2019.historial.cars.historycars.entities.Personal</class>
    <class>sv.edu.fmocc.tpi_2019.historial.cars.historycars.entities.Pieza</class>
    <class>sv.edu.fmocc.tpi_2019.historial.cars.historycars.entities.Proceso</class>
    <class>sv.edu.fmocc.tpi_2019.historial.cars.historycars.entities.Propietario</class>
    <class>sv.edu.fmocc.tpi_2019.historial.cars.historycars.entities.Reparacion</class>
    <class>sv.edu.fmocc.tpi_2019.historial.cars.historycars.entities.SubParte</class>
    <class>sv.edu.fmocc.tpi_2019.historial.cars.historycars.entities.Sucursal</class>
    <class>sv.edu.fmocc.tpi_2019.historial.cars.historycars.entities.TipoPaso</class>
    <class>sv.edu.fmocc.tpi_2019.historial.cars.historycars.entities.TipoVehiculo</class>
    <class>sv.edu.fmocc.tpi_2019.historial.cars.historycars.entities.Vehiculo</class>
    <exclude-unlisted-classes>true</exclude-unlisted-classes>
    <properties/>
  </persistence-unit>
</persistence>
